jupyterlab_github/__init__.py
jupyterlab_github/_version.py
jupyterlab_github/api/api.yaml
jupyterlab_github-4.0.0.data/data/etc/jupyter/jupyter_server_config.d/jupyterlab_github.json
jupyterlab_github-4.0.0.data/data/share/jupyter/labextensions/@jupyterlab/github/package.json
jupyterlab_github-4.0.0.data/data/share/jupyter/labextensions/@jupyterlab/github/schemas/@jupyterlab/github/drive.json
jupyterlab_github-4.0.0.data/data/share/jupyter/labextensions/@jupyterlab/github/schemas/@jupyterlab/github/package.json.orig
jupyterlab_github-4.0.0.data/data/share/jupyter/labextensions/@jupyterlab/github/static/742.36b89fd7ee003ea0f9f1.js
jupyterlab_github-4.0.0.data/data/share/jupyter/labextensions/@jupyterlab/github/static/747.600d6a58e8387735fc09.js
jupyterlab_github-4.0.0.data/data/share/jupyter/labextensions/@jupyterlab/github/static/958.22edf3675e77b075de5c.js
jupyterlab_github-4.0.0.data/data/share/jupyter/labextensions/@jupyterlab/github/static/remoteEntry.3bfd9366a4d281640860.js
jupyterlab_github-4.0.0.data/data/share/jupyter/labextensions/@jupyterlab/github/static/style.js
jupyterlab_github-4.0.0.data/data/share/jupyter/labextensions/@jupyterlab/github/static/third-party-licenses.json
jupyterlab_github-4.0.0.data/data/share/jupyter/labextensions/@jupyterlab/github/install.json
jupyterlab_github-4.0.0.dist-info/METADATA
jupyterlab_github-4.0.0.dist-info/WHEEL
jupyterlab_github-4.0.0.dist-info/licenses/LICENSE
jupyterlab_github-4.0.0.dist-info/RECORD
