Metadata-Version: 2.1
Name: jupyterlab_github
Version: 4.0.0
Summary: JupyterLab viewer for GitHub repositories
Project-URL: Homepage, https://github.com/jupyterlab/jupyterlab-github
Project-URL: Bug Tracker, https://github.com/jupyterlab/jupyterlab-github/issues
Project-URL: Repository, https://github.com/jupyterlab/jupyterlab-github.git
Author-email: Ian Rose <jupyter@googlegroups.com>
License: Copyright (c) 2017, Project Jupyter Contributors
License-File: LICENSE
Classifier: Framework :: Jupyter
Classifier: Framework :: Jupyter :: JupyterLab
Classifier: Framework :: Jupyter :: JupyterLab :: 4
Classifier: Framework :: Jupyter :: JupyterLab :: Extensions
Classifier: Framework :: Jupyter :: JupyterLab :: Extensions :: Prebuilt
Classifier: License :: OSI Approved :: BSD License
Classifier: Programming Language :: Python
Classifier: Programming Language :: Python :: 3
Classifier: Programming Language :: Python :: 3.8
Classifier: Programming Language :: Python :: 3.9
Classifier: Programming Language :: Python :: 3.10
Classifier: Programming Language :: Python :: 3.11
Requires-Python: >=3.8
Requires-Dist: jupyterlab<5,>=4.0.0
